equation_matrix/__init__.py
equation_matrix/calculator.py
equation_matrix-0.1.0.dist-info/METADATA
equation_matrix-0.1.0.dist-info/WHEEL
equation_matrix-0.1.0.dist-info/entry_points.txt
equation_matrix-0.1.0.dist-info/top_level.txt
equation_matrix-0.1.0.dist-info/RECORD
