Metadata-Version: 2.4
Name: equation_matrix
Version: 0.1.0
Summary: A robust and user-friendly Python package for executing diverse mathematical operations with high precision and efficiency.
Author: Debkumar Singha Roy,Sunita Agarwala,Kamal Agarwala
Author-email: debkumar.singha8@gmail.com
Classifier: Programming Language :: Python :: 3
Classifier: License :: OSI Approved :: MIT License
Classifier: Operating System :: OS Independent
Requires-Python: >=3.6
Dynamic: author
Dynamic: author-email
Dynamic: classifier
Dynamic: description
Dynamic: description-content-type
Dynamic: requires-python
Dynamic: summary
